README.rst
setup.py
django_foobar/__init__.py
django_foobar/admin.py
django_foobar/models.py
django_foobar/tests.py
django_foobar/views.py
django_foobar.egg-info/PKG-INFO
django_foobar.egg-info/SOURCES.txt
django_foobar.egg-info/dependency_links.txt
django_foobar.egg-info/not-zip-safe
django_foobar.egg-info/pbr.json
django_foobar.egg-info/requires.txt
django_foobar.egg-info/top_level.txt